[{"_allAttributes":null,"_properties":null,"_methods":null,"file":"/Users/gabboud/Documents/workspace/salesforce.com/lwrfileupload/lwrfileupload/force-app/main/default/lwc/lwrFileUpload/lwrFileUpload.js","metadata":{"decorators":[{"type":"api","targets":[{"name":"acceptedFormats","type":"property","value":{"type":"string","value":"'.pdf', '.jpg', '.png'"}},{"name":"label","type":"property","value":{"type":"string","value":"Attach File(s)"}},{"name":"recordId","type":"property","value":{"type":"unresolved"}},{"name":"multiple","type":"property","value":{"type":"boolean","value":false}},{"name":"disabled","type":"property","value":{"type":"boolean","value":false}},{"name":"fieldName","type":"property","value":{"type":"unresolved"}},{"name":"fieldValue","type":"property","value":{"type":"unresolved"}},{"name":"uploadedFiles","type":"property","value":{"type":"unresolved"}},{"name":"numberOfUploadedFiles","type":"property","value":{"type":"unresolved"}},{"name":"navigateNextOnSuccessfulUpload","type":"property","value":{"type":"boolean","value":false}},{"name":"disableAfterSuccessfulUpload","type":"property","value":{"type":"boolean","value":false}}]}],"classMembers":[{"name":"acceptedFormats","type":"property","value":{"type":"string","value":"'.pdf', '.jpg', '.png'"},"decorator":"api","loc":{"start":{"line":8,"column":4},"end":{"line":8,"column":52}}},{"name":"acceptedFormatsArray","type":"property","loc":{"start":{"line":10,"column":4},"end":{"line":12,"column":5}}},{"name":"showFileUpload","type":"property","loc":{"start":{"line":14,"column":4},"end":{"line":23,"column":5}}},{"name":"label","type":"property","value":{"type":"string","value":"Attach File(s)"},"decorator":"api","loc":{"start":{"line":25,"column":4},"end":{"line":25,"column":34}}},{"name":"recordId","type":"property","value":{"type":"unresolved"},"decorator":"api","loc":{"start":{"line":27,"column":4},"end":{"line":27,"column":18}}},{"name":"multiple","type":"property","value":{"type":"boolean","value":false},"decorator":"api","loc":{"start":{"line":29,"column":4},"end":{"line":29,"column":26}}},{"name":"disabled","type":"property","value":{"type":"boolean","value":false},"decorator":"api","loc":{"start":{"line":31,"column":4},"end":{"line":31,"column":26}}},{"name":"fieldName","type":"property","value":{"type":"unresolved"},"decorator":"api","loc":{"start":{"line":33,"column":4},"end":{"line":33,"column":19}}},{"name":"fieldValue","type":"property","value":{"type":"unresolved"},"decorator":"api","loc":{"start":{"line":35,"column":4},"end":{"line":35,"column":20}}},{"name":"uploadedFiles","type":"property","value":{"type":"unresolved"},"decorator":"api","loc":{"start":{"line":37,"column":4},"end":{"line":37,"column":23}}},{"name":"numberOfUploadedFiles","type":"property","value":{"type":"unresolved"},"decorator":"api","loc":{"start":{"line":39,"column":4},"end":{"line":39,"column":31}}},{"name":"navigateNextOnSuccessfulUpload","type":"property","value":{"type":"boolean","value":false},"decorator":"api","loc":{"start":{"line":41,"column":4},"end":{"line":41,"column":48}}},{"name":"disableAfterSuccessfulUpload","type":"property","value":{"type":"boolean","value":false},"decorator":"api","loc":{"start":{"line":43,"column":4},"end":{"line":43,"column":46}}},{"name":"handleUploadFinished","type":"method","loc":{"start":{"line":45,"column":4},"end":{"line":74,"column":5}}}],"declarationLoc":{"start":{"line":6,"column":0},"end":{"line":76,"column":1}},"doc":"","exports":[{"type":"ExportDefaultDeclaration"}]},"updatedAt":"2024-08-29T18:14:47.757Z"}]